swiftcli/__init__.py
swiftcli/_click_types.py
swiftcli/_pydantic_click_adapter.py
swiftcli/command.py
swiftcli/group.py
swiftcli/py.typed
swiftcli/types.py
swiftcli/utils.py
swiftcli-0.2.0.dist-info/LICENSE
swiftcli-0.2.0.dist-info/METADATA
swiftcli-0.2.0.dist-info/WHEEL
swiftcli-0.2.0.dist-info/RECORD
