Metadata-Version: 2.1
Name: swiftcli
Version: 0.2.0
Summary: Build testable CLI apps with `click` and `pydantic`
License: MIT
Author: Or Levi
Author-email: orlevi128@gmail.com
Requires-Python: >=3.10,<4.0
Classifier: License :: OSI Approved :: MIT License
Classifier: Programming Language :: Python :: 3
Classifier: Programming Language :: Python :: 3.10
Classifier: Programming Language :: Python :: 3.11
Classifier: Programming Language :: Python :: 3.12
Classifier: Programming Language :: Python :: 3.13
Requires-Dist: click (>=8.1.8,<9.0.0)
Requires-Dist: pydantic (>=2.6.0,<3.0.0)
